bareos_restapi_client/__init__.py
bareos_restapi_client/client.py
bareos_restapi_client/models.py
bareos_restapi_client-0.1.22.dist-info/METADATA
bareos_restapi_client-0.1.22.dist-info/WHEEL
bareos_restapi_client-0.1.22.dist-info/top_level.txt
bareos_restapi_client-0.1.22.dist-info/RECORD
